pyorps-0.2.3.dist-info/METADATA
pyorps-0.2.3.dist-info/top_level.txt
pyorps-0.2.3.dist-info/WHEEL
pyorps-0.2.3.dist-info/RECORD
pyorps-0.2.3.dist-info/licenses/LICENSE
pyorps/__init__.py
pyorps/utils/path_core.pyx
pyorps/utils/__init__.py
pyorps/utils/path_algorithms.cpython-312-x86_64-linux-gnu.so
pyorps/utils/path_core.pxd
pyorps/utils/path_algorithms.pyx
pyorps/utils/path_core.cpython-312-x86_64-linux-gnu.so
pyorps/utils/plotting.py
pyorps/utils/path_algorithms.cpp
pyorps/utils/path_core.cpp
pyorps/utils/traversal.py
pyorps/utils/path_algorithms.pxd
pyorps/utils/neighborhood.py
pyorps/core/types.py
pyorps/core/path.py
pyorps/core/cost_assumptions.py
pyorps/core/__init__.py
pyorps/core/exceptions.py
pyorps/graph/__init__.py
pyorps/graph/path_finder.py
pyorps/graph/api/igraph_api.py
pyorps/graph/api/__init__.py
pyorps/graph/api/networkit_api.py
pyorps/graph/api/networkx_api.py
pyorps/graph/api/rustworkx_api.py
pyorps/graph/api/graph_api.py
pyorps/graph/api/cython_api.py
pyorps/graph/api/graph_library_api.py
pyorps/io/__init__.py
pyorps/io/geo_dataset.py
pyorps/io/vector_loader.py
pyorps/raster/handler.py
pyorps/raster/__init__.py
pyorps/raster/rasterizer.py
pyorps.libs/libgomp-24e2ab19.so.1.0.0
