Metadata-Version: 2.4
Name: pyorps
Version: 0.2.3
Summary: PYORPS - (Python for Optimal Routes in Power Systems)
Author-email: Martin Hofmann <martin.hofmann-3@ei.thm.de>
License-Expression: MIT
Project-URL: Homepage, https://github.com/marhofmann/pyorps
Project-URL: Bug Tracker, https://github.com/marhofmann/pyorps/issues
Keywords: power line routing,distribution grid,power systems planning,path finding,rasterized GIS data
Classifier: Development Status :: 3 - Alpha
Classifier: Programming Language :: Python :: 3
Classifier: Programming Language :: Python :: 3.11
Classifier: Programming Language :: Python :: 3.12
Classifier: Topic :: Scientific/Engineering :: GIS
Classifier: Topic :: Scientific/Engineering :: Physics
Requires-Python: >=3.11
License-File: LICENSE
Requires-Dist: numpy>=2.0.0
Requires-Dist: pandas>=2.2.0
Requires-Dist: geopandas>=1.0.0
Requires-Dist: numba>=0.61.0
Requires-Dist: rasterio>=1.4.0
Requires-Dist: matplotlib>=3.10.0
Requires-Dist: requests>=2.32.0
Requires-Dist: defusedxml>=0.7.0
Requires-Dist: psutil>=5.9.0
Provides-Extra: graph
Requires-Dist: rustworkx>=0.16.0; extra == "graph"
Requires-Dist: python-igraph>=0.11.0; extra == "graph"
Requires-Dist: networkx>=3.4.0; extra == "graph"
Requires-Dist: networkit>=11.1; extra == "graph"
Provides-Extra: dev
Requires-Dist: coverage[toml]>=7.8.0; extra == "dev"
Requires-Dist: pytest>=8.3.0; extra == "dev"
Requires-Dist: cython>=3.0.0; extra == "dev"
Provides-Extra: examples
Requires-Dist: notebook>=7.4.0; extra == "examples"
Requires-Dist: fiona>=1.10.0; extra == "examples"
Provides-Extra: case-studies
Requires-Dist: notebook>=7.4.0; extra == "case-studies"
Requires-Dist: fiona>=1.10.0; extra == "case-studies"
Requires-Dist: pandapower>=3.0.0; extra == "case-studies"
Requires-Dist: contextily>=1.6.0; extra == "case-studies"
Provides-Extra: additionals
Requires-Dist: openpyxl>=3.1.0; extra == "additionals"
Provides-Extra: full
Requires-Dist: rustworkx>=0.16.0; extra == "full"
Requires-Dist: python-igraph>=0.11.0; extra == "full"
Requires-Dist: networkx>=3.4.0; extra == "full"
Requires-Dist: networkit>=11.1; extra == "full"
Requires-Dist: coverage[toml]>=7.8.0; extra == "full"
Requires-Dist: pytest>=8.3.0; extra == "full"
Requires-Dist: cython>=3.0.0; extra == "full"
Requires-Dist: notebook>=7.4.0; extra == "full"
Requires-Dist: fiona>=1.10.0; extra == "full"
Requires-Dist: pandapower>=3.0.0; extra == "full"
Requires-Dist: contextily>=1.6.0; extra == "full"
Requires-Dist: openpyxl>=3.1.0; extra == "full"
Dynamic: license-file
